MANIFEST.in
board_hr_recruitment_statistical_view.xml
hr_recruitment_data.xml
hr_recruitment_demo.yml
hr_recruitment_installer_view.xml
hr_recruitment_menu.xml
hr_recruitment_view.xml
res_config_view.xml
setup.py
./__init__.py
./__openerp__.py
./hr_recruitment.py
./res_config.py
./report/__init__.py
./report/hr_recruitment_report.py
./wizard/__init__.py
./wizard/hr_recruitment_create_partner_job.py
./wizard/hr_recruitment_employee_hired.py
i18n/ar.po
i18n/bg.po
i18n/ca.po
i18n/cs.po
i18n/da.po
i18n/de.po
i18n/es.po
i18n/es_CR.po
i18n/es_MX.po
i18n/es_VE.po
i18n/fr.po
i18n/hi.po
i18n/hr.po
i18n/hr_recruitment.pot
i18n/hu.po
i18n/id.po
i18n/it.po
i18n/ja.po
i18n/mk.po
i18n/mn.po
i18n/nb.po
i18n/nl.po
i18n/pl.po
i18n/pt.po
i18n/pt_BR.po
i18n/ro.po
i18n/ru.po
i18n/sl.po
i18n/sr.po
i18n/sr@latin.po
i18n/sv.po
i18n/th.po
i18n/tr.po
i18n/vi.po
i18n/zh_CN.po
i18n/zh_TW.po
images/hr_recruitment_analysis.jpeg
images/hr_recruitment_applicants.jpeg
openerp_hr_recruitment.egg-info/PKG-INFO
openerp_hr_recruitment.egg-info/SOURCES.txt
openerp_hr_recruitment.egg-info/dependency_links.txt
openerp_hr_recruitment.egg-info/requires.txt
openerp_hr_recruitment.egg-info/top_level.txt
report/hr_recruitment_report_view.xml
security/hr_recruitment_security.xml
security/ir.model.access.csv
static/src/img/icon.png
test/recruitment_process.yml
test/resume.eml
wizard/hr_recruitment_create_partner_job_view.xml
wizard/hr_recruitment_employee_hired.xml